JORF_reader/JORF_reader.py
JORF_reader/JOs/joe_20201129_0289_c000.pdf
JORF_reader/JOs/joe_20201206_0295_c000.pdf
JORF_reader/JOs/joe_20201209_0297_c000.pdf
JORF_reader/JOs/joe_20201223_0310_c000.pdf
JORF_reader/JOs/joe_20201227_0313_c000.pdf
JORF_reader/JOs/joe_20210121_0018_c000.pdf
JORF_reader/JOs/joe_20210207_0033_c000.pdf
JORF_reader/JOs/joe_20210217_0041_c000.pdf
JORF_reader/JOs/joe_20210224_0047_c000.pdf
JORF_reader/JOs/joe_20210227_0050_c000.pdf
JORF_reader/JOs/joe_20210307_0057_c000.pdf
JORF_reader/JOs/joe_20210321_0069_c000.pdf
JORF_reader/JOs/joe_20210502_0103_c000.pdf
JORF_reader/JOs/joe_20210508_0108_c000.pdf
JORF_reader/JOs/joe_20210513_0111_c000.pdf
JORF_reader/JOs/joe_20210516_0113_c000.pdf
JORF_reader/JOs/joe_20210528_0122_c000.pdf
JORF_reader/JOs/joe_20210609_0132_c000.pdf
JORF_reader/JOs/joe_20210623_0144_c000.pdf
JORF_reader/JOs/joe_20210627_0148_c000.pdf
JORF_reader/JOs/joe_20210707_0156_c000.pdf
jorf_reader-0.0.3.dist-info/WHEEL
jorf_reader-0.0.3.dist-info/METADATA
jorf_reader-0.0.3.dist-info/RECORD
